py_arkworks_bls12381-0.3.8.dist-info/METADATA
py_arkworks_bls12381-0.3.8.dist-info/WHEEL
py_arkworks_bls12381/__init__.py
py_arkworks_bls12381/py_arkworks_bls12381.cpython-313-arm-linux-gnueabihf.so
py_arkworks_bls12381-0.3.8.dist-info/RECORD
